pytoke/__init__.py
pytoke/pytoke.py
pytoke-0.1.1.dist-info/LICENSE
pytoke-0.1.1.dist-info/METADATA
pytoke-0.1.1.dist-info/WHEEL
pytoke-0.1.1.dist-info/top_level.txt
pytoke-0.1.1.dist-info/RECORD
