Metadata-Version: 2.2
Name: pytoke
Version: 0.1.1
Summary: A library for calculating fertility and parity scores with visualizations using tokenizers.
Home-page: https://github.com/karimnihal/pytoke
Author: Ada Zhang, Nihal Karim, Hamza Louzan, Victor Wei
Author-email: abz200026@gmail.com, karimnihal@gmail.com, hamzalouzan5@gmail.com, victorwei0916@gmail.com
License: MIT
Classifier: Development Status :: 3 - Alpha
Classifier: Programming Language :: Python :: 3
Classifier: Programming Language :: Python :: 3.9
Classifier: Operating System :: OS Independent
Requires-Python: >=3.9
License-File: LICENSE
Requires-Dist: transformers
Requires-Dist: pandas
Requires-Dist: matplotlib
Requires-Dist: numpy
Dynamic: author
Dynamic: author-email
Dynamic: classifier
Dynamic: description
Dynamic: description-content-type
Dynamic: home-page
Dynamic: license
Dynamic: requires-dist
Dynamic: requires-python
Dynamic: summary
